pytuck_view/__init__.py
pytuck_view/__main__.py
pytuck_view/app.py
pytuck_view/api/__init__.py
pytuck_view/api/files.py
pytuck_view/api/tables.py
pytuck_view/base/__init__.py
pytuck_view/base/context.py
pytuck_view/base/exceptions.py
pytuck_view/base/frontend_i18n.py
pytuck_view/base/i18n.py
pytuck_view/base/middleware.py
pytuck_view/base/response.py
pytuck_view/base/schemas.py
pytuck_view/base/setup.py
pytuck_view/services/__init__.py
pytuck_view/services/database.py
pytuck_view/services/file_manager.py
pytuck_view/static/app.css
pytuck_view/static/app.js
pytuck_view/static/components.css
pytuck_view/static/index.html
pytuck_view/static/vue.min.js
pytuck_view/utils/__init__.py
pytuck_view/utils/logger.py
pytuck_view/utils/schemas.py
pytuck_view/utils/tiny_func.py
pytuck_view-0.3.0.dist-info/licenses/LICENSE
pytuck_view-0.3.0.dist-info/METADATA
pytuck_view-0.3.0.dist-info/WHEEL
pytuck_view-0.3.0.dist-info/top_level.txt
pytuck_view-0.3.0.dist-info/RECORD
