Metadata-Version: 2.4
Name: pytuck-view
Version: 0.3.0
Summary: Add your description here
Requires-Python: >=3.12
License-File: LICENSE
Requires-Dist: fastapi>=0.128.0
Requires-Dist: pydantic>=2.12.5
Requires-Dist: pytuck[all]>=0.6.2
Requires-Dist: setuptools>=80.9.0
Requires-Dist: uvicorn>=0.20.0
Dynamic: license-file
